{
  "subject": "AP Physics 2: Algebra-Based",
  "version": "ap_physics_2_2014_2016_2017_2019_2023_2025_v1",
  "units": [
    {
      "code": "U1",
      "name": "Fluids"
    },
    {
      "code": "U2",
      "name": "Thermodynamics"
    },
    {
      "code": "U3",
      "name": "Electric Force, Field, and Potential"
    },
    {
      "code": "U4",
      "name": "Electric Circuits"
    },
    {
      "code": "U5",
      "name": "Magnetism and Electromagnetic Induction"
    },
    {
      "code": "U6",
      "name": "Geometric and Physical Optics"
    },
    {
      "code": "U7",
      "name": "Quantum, Atomic, and Nuclear Physics"
    }
  ],
  "published_mcq_years": [
    2014,
    2016,
    2017,
    2019
  ],
  "published_frq_years": [
    2014,
    2016,
    2017,
    2019,
    2023,
    2024,
    2025
  ],
  "mock_exam": {
    "total_mcq": 40,
    "frq_count": 4,
    "mcq_time_limit": 4800,
    "frq_time_limit": 6000,
    "unit_distribution": {
      "U1": 3,
      "U2": 5,
      "U3": 8,
      "U4": 5,
      "U5": 4,
      "U6": 8,
      "U7": 7
    }
  },
  "notes": [
    "Mock exam uses AP Physics 2 structure: 40 MCQ in 80 minutes and 4 FRQ in 100 minutes.",
    "2016 excludes the unscored MCQ item.",
    "Student-facing prompts and rubrics are structured text; diagrams, graphs, and tables are attached as images or table_data."
  ]
}
